camphr_pipelines/VERSION.py
camphr_pipelines/__init__.py
camphr_pipelines/model_config/knp.yml
camphr_pipelines/model_config/trf_model.yml
camphr_pipelines/model_config/trf_ner.yml
camphr_pipelines/models.py
camphr_pipelines/py.typed
camphr_pipelines-0.1.0.dist-info/WHEEL
camphr_pipelines-0.1.0.dist-info/METADATA
camphr_pipelines-0.1.0.dist-info/RECORD
